lsvtest/__init__.py
lsvtest/constants.py
lsvtest/lsv_recognition.py
lsvtest/utils.py
lsvtest/model/model.h5
lsvtest-0.0.3.dist-info/LICENSE
lsvtest-0.0.3.dist-info/METADATA
lsvtest-0.0.3.dist-info/WHEEL
lsvtest-0.0.3.dist-info/top_level.txt
lsvtest-0.0.3.dist-info/RECORD
