Metadata-Version: 2.1
Name: lsvtest
Version: 0.0.3
Summary: Recognize up to 10 signs of the LSV (Venezuelan Sign Language)
Author-email: Carlos Bone <cdbon15@gmail.com>
License: MIT License
Project-URL: Home, https://github.com/TSX-Corvo/lsv-recognition
Keywords: OpenCV,MediaPipe Holistic,ML,LSV
Classifier: License :: OSI Approved :: MIT License
Requires-Python: >=3.8
License-File: LICENSE
Requires-Dist: mediapipe >=0.10.11
Requires-Dist: opencv-contrib-python >=4.9.0.80
Requires-Dist: opencv-python >=4.9.0.80
Requires-Dist: scikit-learn >=1.4.2
Requires-Dist: tensorflow >=2.16.1
Requires-Dist: tensorflow-io-gcs-filesystem >=0.36.0
